odoo8_addon_base_contact-8.0.2.0.1.99.dev8-py2.7-nspkg.pth
odoo8_addon_base_contact-8.0.2.0.1.99.dev8.dist-info/METADATA
odoo8_addon_base_contact-8.0.2.0.1.99.dev8.dist-info/RECORD
odoo8_addon_base_contact-8.0.2.0.1.99.dev8.dist-info/WHEEL
odoo8_addon_base_contact-8.0.2.0.1.99.dev8.dist-info/namespace_packages.txt
odoo8_addon_base_contact-8.0.2.0.1.99.dev8.dist-info/top_level.txt
odoo_addons/base_contact/README.rst
odoo_addons/base_contact/__init__.py
odoo_addons/base_contact/__openerp__.py
odoo_addons/base_contact/i18n/base_contact.pot
odoo_addons/base_contact/i18n/de.po
odoo_addons/base_contact/i18n/es.po
odoo_addons/base_contact/i18n/eu.po
odoo_addons/base_contact/i18n/fi.po
odoo_addons/base_contact/i18n/fr.po
odoo_addons/base_contact/i18n/it.po
odoo_addons/base_contact/i18n/nl.po
odoo_addons/base_contact/i18n/pt_BR.po
odoo_addons/base_contact/i18n/sl.po
odoo_addons/base_contact/migrations/8.0.2.0/pre-migrate.py
odoo_addons/base_contact/models/__init__.py
odoo_addons/base_contact/models/ir_model.py
odoo_addons/base_contact/static/description/icon.png
