Metadata-Version: 2.1
Name: odoo8-addon-base-contact
Version: 8.0.2.0.1.99.dev8
Summary: [DEPRECATED] Manage your contacts separately
Home-page: http://www.openerp.com
Author: OpenERP SA,Odoo Community Association (OCA)
Author-email: support@odoo-community.org
License: AGPL-3
Platform: UNKNOWN
Classifier: Programming Language :: Python
Classifier: Framework :: Odoo
Classifier: License :: OSI Approved :: GNU Affero General Public License v3
Requires-Python: ~=2.7
Requires-Dist: odoo8-addon-partner-contact-birthdate
Requires-Dist: odoo8-addon-partner-contact-in-several-companies
Requires-Dist: odoo8-addon-partner-contact-nationality
Requires-Dist: odoo (<9.0a,>=8.0a)
